prettier_markdown/__init__.py
prettier_markdown/formatter.py
prettier_markdown/main.py
prettier_markdown-0.1.0.dist-info/licenses/LICENSE
prettier_markdown-0.1.0.dist-info/METADATA
prettier_markdown-0.1.0.dist-info/WHEEL
prettier_markdown-0.1.0.dist-info/entry_points.txt
prettier_markdown-0.1.0.dist-info/top_level.txt
prettier_markdown-0.1.0.dist-info/RECORD
